{
	"format_version": "1.12.0",
	"minecraft:geometry": [
		{
			"description": {
				"identifier": "geometry.player.aa12",
				"texture_width": 164,
				"texture_height": 164,
				"visible_bounds_width": 7,
				"visible_bounds_height": 5,
				"visible_bounds_offset": [0, 0.5, 0]
			},
			"bones": [
				{
					"name": "root",
					"pivot": [0, 0, 0]
				},
				{
					"name": "waist",
					"parent": "root",
					"pivot": [0, 12, 0]
				},
				{
					"name": "body",
					"parent": "waist",
					"pivot": [0, 24, 0]
				},
				{
					"name": "head",
					"parent": "body",
					"pivot": [0, 24, 0]
				},
				{
					"name": "hat",
					"parent": "head",
					"pivot": [0, 24, 0]
				},
				{
					"name": "cape",
					"parent": "body",
					"pivot": [0, 24, 3]
				},
				{
					"name": "leftArm",
					"parent": "body",
					"pivot": [5, 22, 0]
				},
				{
					"name": "leftSleeve",
					"parent": "leftArm",
					"pivot": [5, 22, 0]
				},
				{
					"name": "leftItem",
					"parent": "leftArm",
					"pivot": [6, 15, 1]
				},
				{
					"name": "rightArm",
					"parent": "body",
					"pivot": [-5, 22, 0]
				},
				{
					"name": "tool",
					"parent": "rightArm",
					"pivot": [-5.75, 13, 0],
					"rotation": [90, 0, 0]
				},
				{
					"name": "frame",
					"parent": "tool",
					"pivot": [1, 0, 0]
				},
				{
					"name": "grip",
					"parent": "frame",
					"pivot": [-5.75, 13, 1.50007],
					"rotation": [15, 0, 0],
					"cubes": [
						{"origin": [-6.5, 11.14747, 1.5825], "size": [1.5, 4.92683, 1.41463], "uv": [0, 0]},
						{"origin": [-7, 10.64747, 2.49621], "size": [1.5, 5.92683, 1.5], "inflate": -0.5, "pivot": [-6.5, 13.0743, 2.99621], "rotation": [0, 45, 0], "uv": [1, 0]},
						{"origin": [-6, 10.64747, 2.49621], "size": [1.5, 5.92683, 1.5], "inflate": -0.5, "pivot": [-5, 13.03312, 2.99621], "rotation": [0, -45, 0], "uv": [1, 0]},
						{"origin": [-6.68301, 10.64747, 0.29959], "size": [1.5, 5.92683, 1.5], "inflate": -0.5, "pivot": [-5, 12.03312, 0.61658], "rotation": [0, 45, 0], "uv": [1, 0]},
						{"origin": [-6.31699, 10.64747, 0.29959], "size": [1.5, 5.92683, 1.5], "inflate": -0.5, "pivot": [-6.5, 12.03312, 0.61658], "rotation": [0, -45, 0], "uv": [1, 0]},
						{"origin": [-6.645, 10.64747, 2.34721], "size": [1.79, 5.92683, 1.5], "inflate": -0.5, "uv": [1, 0]},
						{"origin": [-6.64355, 10.64747, 0.72895], "size": [1.79, 5.92683, 1.5], "inflate": -0.5, "uv": [1, 0]}
					]
				},
				{
					"name": "grip2",
					"parent": "frame",
					"pivot": [-5.75, 12.12195, 1.50007],
					"rotation": [30, 0, 0],
					"cubes": [
						{"origin": [-6.5, 9.55338, 1.5513], "size": [1.5, 1.60976, 1.41463], "uv": [0, 0]},
						{"origin": [-7, 9.05338, 2.465], "size": [1.5, 2.60976, 1.5], "inflate": -0.5, "pivot": [-6.5, 12.16313, 2.965], "rotation": [0, 45, 0], "uv": [1, 0]},
						{"origin": [-6, 9.05338, 2.465], "size": [1.5, 2.60976, 1.5], "inflate": -0.5, "pivot": [-5, 12.12195, 2.965], "rotation": [0, -45, 0], "uv": [1, 0]},
						{"origin": [-6.68301, 9.05338, 0.26838], "size": [1.5, 2.60976, 1.5], "inflate": -0.5, "pivot": [-5, 11.12195, 0.58537], "rotation": [0, 45, 0], "uv": [1, 0]},
						{"origin": [-6.31699, 9.05338, 0.26838], "size": [1.5, 2.60976, 1.5], "inflate": -0.5, "pivot": [-6.5, 11.12195, 0.58537], "rotation": [0, -45, 0], "uv": [1, 0]},
						{"origin": [-6.645, 9.05338, 2.316], "size": [1.79, 2.60976, 1.5], "inflate": -0.5, "uv": [1, 0]},
						{"origin": [-6.64355, 9.05338, 0.69774], "size": [1.79, 2.60976, 1.5], "inflate": -0.5, "uv": [1, 0]}
					]
				},
				{
					"name": "grip4",
					"parent": "frame",
					"pivot": [-5.75, 10.46341, 1.50007],
					"rotation": [15, 0, 0],
					"cubes": [
						{"origin": [-6.5, 8.44529, 2.58339], "size": [1.5, 1.60976, 1.41463], "uv": [0, 0]},
						{"origin": [-7, 7.94529, 3.49709], "size": [1.5, 2.60976, 1.5], "inflate": -0.5, "pivot": [-6.5, 11.05504, 3.99709], "rotation": [0, 45, 0], "uv": [1, 0]},
						{"origin": [-6, 7.94529, 3.49709], "size": [1.5, 2.60976, 1.5], "inflate": -0.5, "pivot": [-5, 11.01386, 3.99709], "rotation": [0, -45, 0], "uv": [1, 0]},
						{"origin": [-6.68301, 7.94529, 1.30048], "size": [1.5, 2.60976, 1.5], "inflate": -0.5, "pivot": [-5, 10.01386, 1.61747], "rotation": [0, 45, 0], "uv": [1, 0]},
						{"origin": [-6.31699, 7.94529, 1.30048], "size": [1.5, 2.60976, 1.5], "inflate": -0.5, "pivot": [-6.5, 10.01386, 1.61747], "rotation": [0, -45, 0], "uv": [1, 0]},
						{"origin": [-6.645, 7.94529, 3.34809], "size": [1.79, 2.60976, 1.5], "inflate": -0.5, "uv": [1, 0]},
						{"origin": [-6.64355, 7.94529, 1.72984], "size": [1.79, 2.60976, 1.5], "inflate": -0.5, "uv": [1, 0]}
					]
				},
				{
					"name": "grip5",
					"parent": "frame",
					"pivot": [-5.75, 9.39024, 2.47568],
					"cubes": [
						{"origin": [-6.50145, 7.64208, 3.01114], "size": [1.5, 1.60976, 1.41463], "uv": [0, 0]},
						{"origin": [-7.00145, 7.14208, 3.92485], "size": [1.5, 2.60976, 1.5], "inflate": -0.5, "pivot": [-6.50145, 10.25184, 4.42485], "rotation": [0, 45, 0], "uv": [1, 0]},
						{"origin": [-6.00145, 7.14208, 3.92485], "size": [1.5, 2.60976, 1.5], "inflate": -0.5, "pivot": [-5.00145, 10.21066, 4.42485], "rotation": [0, -45, 0], "uv": [1, 0]},
						{"origin": [-6.68446, 7.14208, 1.72823], "size": [1.5, 2.60976, 1.5], "inflate": -0.5, "pivot": [-5.00145, 9.21066, 2.04522], "rotation": [0, 45, 0], "uv": [1, 0]},
						{"origin": [-6.31844, 7.14208, 1.72823], "size": [1.5, 2.60976, 1.5], "inflate": -0.5, "pivot": [-6.50145, 9.21066, 2.04522], "rotation": [0, -45, 0], "uv": [1, 0]},
						{"origin": [-6.64645, 7.14208, 3.77585], "size": [1.79, 2.60976, 1.5], "inflate": -0.5, "uv": [1, 0]},
						{"origin": [-6.645, 7.14208, -3.20826], "size": [1.79, 1.34146, 6.86585], "inflate": -0.5, "uv": [1, 0]},
						{"origin": [-6.645, 7.14208, 2.15759], "size": [1.79, 2.60976, 1.5], "inflate": -0.5, "uv": [1, 0]}
					]
				},
				{
					"name": "grip3",
					"parent": "frame",
					"pivot": [-5.75, 16.70732, 1.98787],
					"rotation": [-7.5, 0, 0],
					"cubes": [
						{"origin": [-6.5, 13.26069, 2.0391], "size": [1.5, 2.19512, 1.41463], "uv": [0, 0]},
						{"origin": [-7, 12.76069, 2.9528], "size": [1.5, 3.19512, 1.5], "inflate": -0.5, "pivot": [-6.5, 16.7485, 3.4528], "rotation": [0, 45, 0], "uv": [1, 0]},
						{"origin": [-6, 12.76069, 2.9528], "size": [1.5, 3.19512, 1.5], "inflate": -0.5, "pivot": [-5, 16.70732, 3.4528], "rotation": [0, -45, 0], "uv": [1, 0]},
						{"origin": [-6.68301, 12.76069, 0.75619], "size": [1.5, 3.19512, 1.5], "inflate": -0.5, "pivot": [-5, 15.70732, 1.07318], "rotation": [0, 45, 0], "uv": [1, 0]},
						{"origin": [-6.31699, 12.76069, 0.75619], "size": [1.5, 3.19512, 1.5], "inflate": -0.5, "pivot": [-6.5, 15.70732, 1.07318], "rotation": [0, -45, 0], "uv": [1, 0]},
						{"origin": [-6.645, 12.76069, 2.8038], "size": [1.79, 3.19512, 1.5], "inflate": -0.5, "uv": [1, 0]},
						{"origin": [-6.64355, 12.76069, 1.18555], "size": [1.79, 3.19512, 1.5], "inflate": -0.5, "uv": [1, 0]}
					]
				},
				{
					"name": "ammo",
					"parent": "frame",
					"pivot": [7.63415, -15.02439, -11.5122],
					"cubes": [
						{"origin": [-6.48585, 12.57756, -5.74927], "size": [1.6, 3.2, 2.51707], "uv": [6, 0]},
						{"origin": [-4.67837, 7.79473, -5.74927], "size": [1.6, 3.2, 2.51707], "pivot": [-1.2031, 10.71682, -2.52976], "rotation": [0, 0, 67.5], "uv": [6, 0]},
						{"origin": [-4.5883, 2.80743, -5.74927], "size": [1.6, 3.2, 2.51707], "pivot": [0.14799, 7.8194, -2.52976], "rotation": [0, 0, 90], "uv": [6, 0]},
						{"origin": [-3.06429, 7.30098, -5.74927], "size": [1.6, 3.2, 2.51707], "pivot": [-4.29897, 8.97891, -2.52976], "rotation": [0, 0, -67.5], "uv": [6, 0]},
						{"origin": [-3.94863, 7.9833, -5.74927], "size": [1.6, 3.2, 2.51707], "pivot": [-4.11609, 8.81773, -2.52976], "rotation": [0, 0, -45], "uv": [6, 0]},
						{"origin": [-5.15012, 8.13529, -5.74927], "size": [1.6, 3.2, 2.51707], "pivot": [-4.00881, 8.59883, -2.52976], "rotation": [0, 0, -22.5], "uv": [6, 0]},
						{"origin": [-6.48585, 7.73382, -5.74927], "size": [1.6, 3.2, 2.51707], "uv": [6, 0]},
						{"origin": [-7.75248, 6.84, -5.74927], "size": [1.6, 3.2, 2.51707], "pivot": [-4.07239, 8.1249, -2.52976], "rotation": [0, 0, 22.5], "uv": [6, 0]},
						{"origin": [-8.75716, 5.5899, -5.74927], "size": [1.6, 3.2, 2.51707], "pivot": [-4.23357, 7.94202, -2.52976], "rotation": [0, 0, 45], "uv": [6, 0]},
						{"origin": [-9.34695, 4.17385, -5.74927], "size": [1.6, 3.2, 2.51707], "pivot": [-4.45247, 7.83474, -2.52976], "rotation": [0, 0, 67.5], "uv": [6, 0]},
						{"origin": [-7.00374, 12.61033, -5.74927], "size": [1.6, 3.2, 2.51707], "pivot": [-5.86243, 13.07387, -2.52976], "rotation": [0, 0, -22.5], "uv": [6, 0]},
						{"origin": [-7.37367, 11.40834, -5.74927], "size": [1.6, 3.2, 2.51707], "pivot": [-7.54113, 12.24277, -2.52976], "rotation": [0, 0, -45], "uv": [6, 0]},
						{"origin": [-7.52638, 9.21968, -5.74927], "size": [1.6, 3.2, 2.51707], "pivot": [-8.76106, 10.89761, -2.52976], "rotation": [0, 0, -67.5], "uv": [6, 0]},
						{"origin": [-7.46255, 6.25728, -5.74927], "size": [1.6, 3.2, 2.51707], "pivot": [-9.36041, 9.12291, -2.52976], "rotation": [0, 0, -90], "uv": [6, 0]},
						{"origin": [-7.4755, 6.19221, -5.74927], "size": [1.6, 3.2, 2.51707], "pivot": [-9.37335, 9.05783, -2.52976], "rotation": [0, 0, -90], "uv": [6, 0]},
						{"origin": [-16.19676, 9.98159, -5.74927], "size": [1.6, 3.2, 2.51707], "pivot": [-4.01589, -13.9523, 1.79024], "rotation": [0, 0, 22.5], "uv": [6, 0]},
						{"origin": [-25.65432, 10.3904, -5.74927], "size": [1.6, 3.2, 2.51707], "pivot": [-12.62995, -12.47628, 1.79024], "rotation": [0, 0, 45], "uv": [6, 0]}
					]
				},
				{
					"name": "ammo2",
					"parent": "frame",
					"pivot": [7.63415, -15.02439, -11.5122],
					"cubes": [
						{"origin": [-6.48585, 12.57756, -3.52488], "size": [1.6, 3.2, 0.4878], "inflate": 0.20732, "uv": [2, 162]},
						{"origin": [-4.67837, 7.79473, -3.52488], "size": [1.6, 3.2, 0.4878], "inflate": 0.20732, "pivot": [-1.2031, 10.71682, -2.52976], "rotation": [0, 0, 67.5], "uv": [2, 162]},
						{"origin": [-4.5883, 2.80743, -3.52488], "size": [1.6, 3.2, 0.4878], "inflate": 0.20732, "pivot": [0.14799, 7.8194, -2.52976], "rotation": [0, 0, 90], "uv": [2, 162]},
						{"origin": [-3.06429, 7.30098, -3.52488], "size": [1.6, 3.2, 0.4878], "inflate": 0.20732, "pivot": [-4.29897, 8.97891, -2.52976], "rotation": [0, 0, -67.5], "uv": [2, 162]},
						{"origin": [-3.94863, 7.9833, -3.52488], "size": [1.6, 3.2, 0.4878], "inflate": 0.20732, "pivot": [-4.11609, 8.81773, -2.52976], "rotation": [0, 0, -45], "uv": [2, 162]},
						{"origin": [-5.15012, 8.13529, -3.52488], "size": [1.6, 3.2, 0.4878], "inflate": 0.20732, "pivot": [-4.00881, 8.59883, -2.52976], "rotation": [0, 0, -22.5], "uv": [2, 162]},
						{"origin": [-6.48585, 7.73382, -3.52488], "size": [1.6, 3.2, 0.4878], "inflate": 0.20732, "uv": [2, 162]},
						{"origin": [-7.75248, 6.84, -3.52488], "size": [1.6, 3.2, 0.4878], "inflate": 0.20732, "pivot": [-4.07239, 8.1249, -2.52976], "rotation": [0, 0, 22.5], "uv": [2, 162]},
						{"origin": [-8.75716, 5.5899, -3.52488], "size": [1.6, 3.2, 0.4878], "inflate": 0.20732, "pivot": [-4.23357, 7.94202, -2.52976], "rotation": [0, 0, 45], "uv": [2, 162]},
						{"origin": [-9.34695, 4.17385, -3.52488], "size": [1.6, 3.2, 0.4878], "inflate": 0.20732, "pivot": [-4.45247, 7.83474, -2.52976], "rotation": [0, 0, 67.5], "uv": [2, 162]},
						{"origin": [-7.00374, 12.61033, -3.52488], "size": [1.6, 3.2, 0.4878], "inflate": 0.20732, "pivot": [-5.86243, 13.07387, -2.52976], "rotation": [0, 0, -22.5], "uv": [2, 162]},
						{"origin": [-7.37367, 11.40834, -3.52488], "size": [1.6, 3.2, 0.4878], "inflate": 0.20732, "pivot": [-7.54113, 12.24277, -2.52976], "rotation": [0, 0, -45], "uv": [2, 162]},
						{"origin": [-7.52638, 9.21968, -3.52488], "size": [1.6, 3.2, 0.4878], "inflate": 0.20732, "pivot": [-8.76106, 10.89761, -2.52976], "rotation": [0, 0, -67.5], "uv": [2, 162]},
						{"origin": [-7.46255, 6.25728, -3.52488], "size": [1.6, 3.2, 0.4878], "inflate": 0.20732, "pivot": [-9.36041, 9.12291, -2.52976], "rotation": [0, 0, -90], "uv": [2, 162]},
						{"origin": [-7.4755, 6.19221, -3.52488], "size": [1.6, 3.2, 0.4878], "inflate": 0.20732, "pivot": [-9.37335, 9.05783, -2.52976], "rotation": [0, 0, -90], "uv": [2, 162]},
						{"origin": [-16.19676, 9.98159, -3.52488], "size": [1.6, 3.2, 0.4878], "inflate": 0.20732, "pivot": [-4.01589, -13.9523, 1.79024], "rotation": [0, 0, 22.5], "uv": [2, 162]},
						{"origin": [-25.65432, 10.3904, -3.52488], "size": [1.6, 3.2, 0.4878], "inflate": 0.20732, "pivot": [-12.62995, -12.47628, 1.79024], "rotation": [0, 0, 45], "uv": [2, 162]}
					]
				},
				{
					"name": "base",
					"parent": "frame",
					"pivot": [-5.75, 10.65, -1.5]
				},
				{
					"name": "wooden0",
					"parent": "base",
					"pivot": [-5.75, 13.3, -19.64634],
					"cubes": [
						{"origin": [-8.17828, 13.85413, -18.85366], "size": [1.35, 1.35, 36.54878], "inflate": -0.5, "pivot": [-5, 12.37585, -9.5], "rotation": [0, 0, 45], "uv": [29, 1]},
						{"origin": [-6.74749, 14.92105, -18.85366], "size": [2, 1.25, 36.54878], "inflate": -0.5, "uv": [28, 1]},
						{"origin": [-6.74749, 17.66237, 1.53659], "size": [2, 1.34756, 3.37805], "inflate": -0.5, "uv": [0, 161]},
						{"origin": [-6.74749, 12.05643, -18.42305], "size": [1.21951, 1.34756, 6.0122], "inflate": -0.5, "pivot": [0.00251, -0.55865, -0.01687], "rotation": [-60, 0, 0], "uv": [0, 158]},
						{"origin": [-6.74749, -15.2129, -25.06391], "size": [2, 1.93293, 6.0122], "inflate": -0.5, "pivot": [0.00251, -0.6523, -0.1967], "rotation": [-80, 0, 0], "uv": [0, 158]},
						{"origin": [-6.74749, -19.36175, -22.14064], "size": [2, 1.93293, 6.0122], "inflate": -0.5, "pivot": [0.00251, -0.55865, -0.01687], "rotation": [-90, 0, 0], "uv": [0, 158]},
						{"origin": [-5.77188, -18.502, -22.04308], "size": [0.04878, 0, 3.96341], "pivot": [0.00251, -0.55865, -0.01687], "rotation": [-90, 0, 0], "uv": [2, 162]},
						{"origin": [-5.967, 12.05643, -18.42305], "size": [1.21951, 1.34756, 6.0122], "inflate": -0.5, "pivot": [0.00251, -0.55865, -0.01687], "rotation": [-60, 0, 0], "uv": [0, 158]},
						{"origin": [-6.74749, 2.10659, -23.55954], "size": [2, 1.9329, 1.32927], "inflate": -0.5, "pivot": [0.00251, -0.26458, -1.11508], "rotation": [-90, 0, 0], "uv": [0, 163]},
						{"origin": [-6.74749, 2.10659, -23.59031], "size": [2, 1.9329, 1.32927], "inflate": -0.5, "pivot": [0.00251, -0.26458, -1.14585], "rotation": [-90, 0, 0], "uv": [6, 163]},
						{"origin": [-6.74749, 2.20415, -23.68788], "size": [1.21951, 1.34756, 6.20732], "inflate": -0.5, "pivot": [0.00251, -0.26458, -1.24341], "rotation": [-90, 0, 0], "uv": [1, 158]},
						{"origin": [-5.86944, 2.20415, -23.68788], "size": [1.12195, 1.34756, 6.20732], "inflate": -0.5, "pivot": [0.00251, -0.26458, -1.24341], "rotation": [-90, 0, 0], "uv": [1, 158]},
						{"origin": [-6.74749, 17.66237, -18.85366], "size": [2, 1.25, 36.54878], "inflate": -0.5, "uv": [28, 1]},
						{"origin": [-4.87365, 13.93986, -18.85366], "size": [1.35, 1.35, 36.54878], "inflate": -0.5, "pivot": [-6.49497, 12.66854, -9.5], "rotation": [0, 0, -45], "uv": [29, 1]},
						{"origin": [-10.15109, 16.35757, -18.85366], "size": [1.35, 1.35, 36.54878], "inflate": -0.5, "pivot": [-6.49497, 13.70146, -9.5], "rotation": [0, 0, 45], "uv": [29, 1]},
						{"origin": [-6.99497, 15.16854, -0.80488], "size": [2.32561, 3.49634, 18.5], "inflate": -0.5, "uv": [29, 1]},
						{"origin": [-6.99497, 15.16854, -18.85366], "size": [2.32561, 3.49634, 14.89024], "inflate": -0.5, "uv": [29, 1]},
						{"origin": [-6.99497, 16.72951, -18.85366], "size": [2.32561, 1.93537, 19.86585], "inflate": -0.5, "uv": [29, 1]},
						{"origin": [-6.99497, 14.97341, -18.85366], "size": [2.32561, 1.74024, 19.86585], "inflate": -0.5, "uv": [29, 1]},
						{"origin": [-6.89741, 15.55878, -6.7561], "size": [2.32561, 2.22805, 7.76829], "inflate": -0.5, "uv": [0, 157]},
						{"origin": [-5.85, 15.16854, -18.85366], "size": [1.35, 3.49634, 36.54878], "inflate": -0.5, "uv": [29, 1]},
						{"origin": [-7.11829, 14.68467, -15.82018], "size": [2.71585, 3.1061, 8.15854], "inflate": -0.5, "pivot": [-4.31521, 13.29623, -9.68603], "rotation": [-5, 0, 0], "uv": [145, 154]},
						{"origin": [-7.11829, 15.16854, -15.63415], "size": [2.71585, 3.1061, 8.35366], "inflate": -0.5, "uv": [145, 154]},
						{"origin": [-7.11829, 14.52585, -8.5122], "size": [2.71585, 1.64268, 1.23171], "inflate": -0.5, "uv": [156, 163]},
						{"origin": [-7.11829, 15.16854, -15.63415], "size": [2.71585, 3.1061, 8.15854], "inflate": -0.5, "uv": [145, 154]},
						{"origin": [-2.69389, 16.35757, -18.85366], "size": [1.35, 1.35, 36.54878], "inflate": -0.5, "pivot": [-5, 13.70146, -9.5], "rotation": [0, 0, -45], "uv": [29, 1]}
					]
				},
				{
					"name": "wooden4",
					"parent": "base",
					"pivot": [-5.75, 13.76341, -3.54878],
					"cubes": [
						{"origin": [-6.05696, 9.69988, 15.5], "size": [1.35, 1.35, 2.19512], "inflate": -0.5, "pivot": [-5, 10.34293, -3.54878], "rotation": [0, 0, 45], "uv": [126, 106]},
						{"origin": [-6.74749, 9.88812, 15.5], "size": [2, 8.85976, 2.19512], "inflate": -0.5, "uv": [126, 106]},
						{"origin": [-6.74749, 12.62944, 15.5], "size": [2, 1.25, 2.19512], "inflate": -0.5, "uv": [126, 106]},
						{"origin": [-6.99497, 9.78561, 15.5], "size": [1.35, 1.35, 2.19512], "inflate": -0.5, "pivot": [-6.49497, 10.63561, -3.54878], "rotation": [0, 0, -45], "uv": [126, 106]},
						{"origin": [-8.02977, 12.20333, 15.5], "size": [1.35, 1.35, 2.19512], "inflate": -0.5, "pivot": [-6.49497, 11.66854, -3.54878], "rotation": [0, 0, 45], "uv": [126, 106]},
						{"origin": [-6.99497, 10.13561, 15.5], "size": [2.42317, 7.78902, 2.19512], "inflate": -0.5, "uv": [126, 106]},
						{"origin": [-5.85, 10.13561, 15.5], "size": [1.35, 7.78902, 2.19512], "inflate": -0.5, "uv": [126, 106]},
						{"origin": [-4.81521, 12.20333, 15.5], "size": [1.35, 1.35, 2.19512], "inflate": -0.5, "pivot": [-5, 11.66854, -3.54878], "rotation": [0, 0, -45], "uv": [126, 106]}
					]
				},
				{
					"name": "wooden2",
					"parent": "base",
					"pivot": [-5.75, 14.25122, -9.5],
					"cubes": [
						{"origin": [-6.05696, 12.68403, -3.23171], "size": [1.35, 1.35, 6.4878], "inflate": -0.5, "pivot": [-5, 13.32707, -9.5], "rotation": [0, 0, 45], "uv": [29, 1]},
						{"origin": [-6.74749, 12.87227, -3.23171], "size": [2, 1.25, 6.4878], "inflate": -0.5, "uv": [28, 1]},
						{"origin": [-6.74749, 15.61358, -3.23171], "size": [2, 1.25, 6.4878], "inflate": -0.5, "uv": [28, 1]},
						{"origin": [-6.99497, 12.76976, -3.23171], "size": [1.35, 1.35, 6.4878], "inflate": -0.5, "pivot": [-6.49497, 13.61976, -9.5], "rotation": [0, 0, -45], "uv": [29, 1]},
						{"origin": [-8.02977, 15.18747, -3.23171], "size": [1.35, 1.35, 6.4878], "inflate": -0.5, "pivot": [-6.49497, 14.65268, -9.5], "rotation": [0, 0, 45], "uv": [29, 1]},
						{"origin": [-6.99497, 13.11976, -3.23171], "size": [1.35, 3.49634, 6.4878], "inflate": -0.5, "uv": [29, 1]},
						{"origin": [-5.85, 13.11976, -3.23171], "size": [1.35, 3.49634, 6.4878], "inflate": -0.5, "uv": [29, 1]},
						{"origin": [-4.81521, 15.18747, -3.23171], "size": [1.35, 1.35, 6.4878], "inflate": -0.5, "pivot": [-5, 14.65268, -9.5], "rotation": [0, 0, -45], "uv": [29, 1]}
					]
				},
				{
					"name": "wooden6",
					"parent": "base",
					"pivot": [-5.75, 12.7878, -5.30488],
					"rotation": [30, 0, 0],
					"cubes": [
						{"origin": [-6.05696, 8.54208, 1.59211], "size": [1.35, 1.35, 5.21951], "inflate": -0.5, "pivot": [-5, 9.18513, -4.67619], "rotation": [0, 0, 45], "uv": [29, 1]},
						{"origin": [-6.74749, 8.73032, 1.59211], "size": [2, 1.25, 5.21951], "inflate": -0.5, "uv": [28, 1]},
						{"origin": [-6.74749, 11.47164, 1.59211], "size": [2, 1.25, 5.21951], "inflate": -0.5, "uv": [28, 1]},
						{"origin": [-6.99497, 8.62781, 1.59211], "size": [1.35, 1.35, 5.21951], "inflate": -0.5, "pivot": [-6.49497, 9.47781, -4.67619], "rotation": [0, 0, -45], "uv": [29, 1]},
						{"origin": [-8.02977, 11.04553, 1.59211], "size": [1.35, 1.35, 5.21951], "inflate": -0.5, "pivot": [-6.49497, 10.51073, -4.67619], "rotation": [0, 0, 45], "uv": [29, 1]},
						{"origin": [-6.99497, 8.97781, 1.59211], "size": [1.35, 3.49634, 5.21951], "inflate": -0.5, "uv": [29, 1]},
						{"origin": [-5.85, 8.97781, 1.59211], "size": [1.35, 3.49634, 5.21951], "inflate": -0.5, "uv": [29, 1]},
						{"origin": [-4.81521, 11.04553, 1.59211], "size": [1.35, 1.35, 5.21951], "inflate": -0.5, "pivot": [-5, 10.51073, -4.67619], "rotation": [0, 0, -45], "uv": [29, 1]}
					]
				},
				{
					"name": "wooden7",
					"parent": "base",
					"pivot": [-5.75, 16.98293, -4.13415],
					"rotation": [5, 0, 0],
					"cubes": [
						{"origin": [-6.05696, 12.73721, 2.76284], "size": [1.35, 1.35, 5.21951], "inflate": -0.5, "pivot": [-5, 13.38025, -3.50545], "rotation": [0, 0, 45], "uv": [29, 1]},
						{"origin": [-6.74749, 12.92544, 2.76284], "size": [2, 1.25, 5.21951], "inflate": -0.5, "uv": [28, 1]},
						{"origin": [-6.74749, 15.66676, 2.76284], "size": [2, 1.25, 5.21951], "inflate": -0.5, "uv": [28, 1]},
						{"origin": [-6.99497, 12.82293, 2.76284], "size": [1.35, 1.35, 5.21951], "inflate": -0.5, "pivot": [-6.49497, 13.67293, -3.50545], "rotation": [0, 0, -45], "uv": [29, 1]},
						{"origin": [-8.02977, 15.24065, 2.76284], "size": [1.35, 1.35, 5.21951], "inflate": -0.5, "pivot": [-6.49497, 14.70586, -3.50545], "rotation": [0, 0, 45], "uv": [29, 1]},
						{"origin": [-6.99497, 13.17293, 2.76284], "size": [1.35, 3.49634, 5.21951], "inflate": -0.5, "uv": [29, 1]},
						{"origin": [-5.85, 13.17293, 2.76284], "size": [1.35, 3.49634, 5.21951], "inflate": -0.5, "uv": [29, 1]},
						{"origin": [-4.81521, 15.24065, 2.76284], "size": [1.35, 1.35, 5.21951], "inflate": -0.5, "pivot": [-5, 14.70586, -3.50545], "rotation": [0, 0, -45], "uv": [29, 1]}
					]
				},
				{
					"name": "wooden5",
					"parent": "base",
					"pivot": [-5.75, 8.49512, -4.03659],
					"rotation": [-20, 0, 0],
					"cubes": [
						{"origin": [-6.05696, 16.43864, 0.1564], "size": [1.35, 1.35, 14.4878], "inflate": -0.5, "pivot": [-5, 17.08168, 1.8881], "rotation": [0, 0, 45], "uv": [29, 1]},
						{"origin": [-6.74749, 16.62688, 0.1564], "size": [2, 1.25, 14.4878], "inflate": -0.5, "uv": [28, 1]},
						{"origin": [-6.74749, 19.36819, 0.1564], "size": [2, 1.25, 14.4878], "inflate": -0.5, "uv": [28, 1]},
						{"origin": [-6.99497, 16.52436, 0.1564], "size": [1.35, 1.35, 14.4878], "inflate": -0.5, "pivot": [-6.49497, 17.37436, 1.8881], "rotation": [0, 0, -45], "uv": [29, 1]},
						{"origin": [-8.02977, 18.94208, 0.1564], "size": [1.35, 1.35, 14.4878], "inflate": -0.5, "pivot": [-6.49497, 18.40729, 1.8881], "rotation": [0, 0, 45], "uv": [29, 1]},
						{"origin": [-6.99497, 16.87436, 0.1564], "size": [1.35, 3.49634, 14.4878], "inflate": -0.5, "uv": [29, 1]},
						{"origin": [-5.85, 16.87436, 0.1564], "size": [1.35, 3.49634, 14.4878], "inflate": -0.5, "uv": [29, 1]},
						{"origin": [-5.85, 16.87436, 6.10762], "size": [1.35, 6.22805, 7.7561], "inflate": -0.5, "uv": [29, 1]},
						{"origin": [-6.99497, 17.15749, 5.46667], "size": [1.35, 5.74024, 8.2439], "inflate": -0.5, "uv": [29, 1]},
						{"origin": [-4.81521, 18.94208, 0.1564], "size": [1.35, 1.35, 14.4878], "inflate": -0.5, "pivot": [-5, 18.40729, 1.8881], "rotation": [0, 0, -45], "uv": [29, 1]}
					]
				},
				{
					"name": "wooden3",
					"parent": "base",
					"pivot": [-5.75, 14.83659, -9.69512],
					"rotation": [-5, 0, 0],
					"cubes": [
						{"origin": [-6.79991, 15.46071, -18.90403], "size": [1.35, 1.35, 13.80488], "inflate": -0.5, "pivot": [-7.53659, 14.31011, -17.36744], "rotation": [0, 0, 45], "uv": [29, 1]},
						{"origin": [-6.74749, 13.85531, -18.90403], "size": [2, 1.25, 13.80488], "inflate": -0.5, "uv": [28, 1]},
						{"origin": [-6.74749, 16.59662, -18.90403], "size": [2, 1.25, 13.80488], "inflate": -0.5, "uv": [28, 1]},
						{"origin": [-7.73792, 11.95916, -18.90403], "size": [1.35, 1.35, 13.80488], "inflate": -0.5, "pivot": [-9.03156, 14.60279, -17.36744], "rotation": [0, 0, -45], "uv": [29, 1]},
						{"origin": [-8.77271, 17.96415, -18.90403], "size": [1.35, 1.35, 13.80488], "inflate": -0.5, "pivot": [-9.03156, 15.63572, -17.36744], "rotation": [0, 0, 45], "uv": [29, 1]},
						{"origin": [-6.99497, 14.10279, -18.90403], "size": [2.32561, 3.49634, 13.80488], "inflate": -0.5, "uv": [29, 1]},
						{"origin": [-5.85, 14.10279, -18.90403], "size": [1.35, 3.49634, 13.80488], "inflate": -0.5, "uv": [29, 1]},
						{"origin": [-5.55816, 14.37687, -18.90403], "size": [1.35, 1.35, 13.80488], "inflate": -0.5, "pivot": [-7.53659, 15.63572, -17.36744], "rotation": [0, 0, -45], "uv": [29, 1]}
					]
				},
				{
					"name": "wooden1",
					"parent": "base",
					"pivot": [-5.75, 17.68, -9.5]
				},
				{
					"name": "trigger",
					"parent": "frame",
					"pivot": [-5.75, 11.03659, -2.18333],
					"cubes": [
						{"origin": [-6.645, 11.33659, -2.89024], "size": [1.79, 1.2, 5.54878], "inflate": -0.5, "uv": [9, 18]},
						{"origin": [-6.645, 7.23902, -3.2], "size": [1.79, 7.09756, 1.40976], "inflate": -0.5, "uv": [11, 18]},
						{"origin": [-6.4, 12.27919, -0.48137], "size": [1.3, 2.40244, 1.2], "inflate": -0.5, "pivot": [-5.75, 13.2961, -0.65], "rotation": [-10, 0, 0], "uv": [11, 19]},
						{"origin": [-6.4, 13.00647, -0.53656], "size": [1.3, 1.81707, 1.2], "inflate": -0.5, "pivot": [-5.75, 13.2961, -0.65], "rotation": [-32.5, 0, 0], "uv": [11, 19]},
						{"origin": [-6.4, 12.28691, -0.65449], "size": [1.3, 1.81707, 1.2], "inflate": -0.5, "pivot": [-5.75, 13.2961, -0.65], "rotation": [22.5, 0, 0], "uv": [11, 19]},
						{"origin": [-6.4, 12.44674, -0.40891], "size": [1.3, 1.32927, 1.2], "inflate": -0.5, "pivot": [-5.75, 13.23429, -0.81122], "rotation": [-35, 0, 0], "uv": [11, 19]}
					]
				},
				{
					"name": "barrel",
					"parent": "tool",
					"pivot": [0, 0, 0]
				},
				{
					"name": "hole",
					"parent": "barrel",
					"pivot": [-5.73025, 17.40599, -14.67073],
					"cubes": [
						{"origin": [-6.36477, 16.50586, -19.53627], "size": [1.26957, 1.1152, 8.07274], "inflate": -0.5, "uv": [147, 156]},
						{"origin": [-9.84245, 15.88464, -19.53627], "size": [1.26957, 1.1152, 8.07274], "inflate": -0.5, "pivot": [-5.9073, 7.39112, -5.16673], "rotation": [0, 0, 22.5], "uv": [147, 156]},
						{"origin": [-12.11218, 13.79051, -19.53627], "size": [1.26957, 1.1152, 8.07274], "inflate": -0.5, "pivot": [-5.32598, 8.14804, -5.16673], "rotation": [0, 0, 45], "uv": [147, 156]},
						{"origin": [-15.31745, 14.26735, -19.53627], "size": [1.26957, 1.1152, 8.07274], "inflate": -0.5, "pivot": [-8.53125, 8.62488, -5.16673], "rotation": [0, 0, 67.5], "uv": [147, 156]},
						{"origin": [-5.66759, 16.07823, -19.53627], "size": [1.26957, 1.1152, 8.07274], "inflate": -0.5, "pivot": [-5.16759, 16.57823, -17.96798], "rotation": [0, 0, 90], "uv": [147, 156]},
						{"origin": [-6.9076, 16.07823, -19.53627], "size": [1.26957, 1.1152, 8.07274], "inflate": -0.5, "pivot": [-6.4076, 16.57823, -17.96798], "rotation": [0, 0, 90], "uv": [147, 156]},
						{"origin": [-5.65555, 15.55962, -19.53627], "size": [1.26957, 1.1152, 8.07274], "inflate": -0.5, "pivot": [-5.15555, 16.05962, -17.96798], "rotation": [0, 0, -67.5], "uv": [147, 156]},
						{"origin": [-6.80116, 16.03415, -19.53627], "size": [1.26957, 1.1152, 8.07274], "inflate": -0.5, "pivot": [-6.30116, 16.53415, -17.96798], "rotation": [0, 0, -67.5], "uv": [147, 156]},
						{"origin": [-5.84616, 15.369, -19.53627], "size": [1.26957, 1.1152, 8.07274], "inflate": -0.5, "pivot": [-5.34616, 15.869, -17.96798], "rotation": [0, 0, -45], "uv": [147, 156]},
						{"origin": [-6.72298, 16.24582, -19.53627], "size": [1.26957, 1.1152, 8.07274], "inflate": -0.5, "pivot": [-6.22298, 16.74582, -17.96798], "rotation": [0, 0, -45], "uv": [147, 156]},
						{"origin": [-6.09521, 15.26585, -19.53627], "size": [1.26957, 1.1152, 8.07274], "inflate": -0.5, "pivot": [-5.59521, 15.76585, -17.96798], "rotation": [0, 0, -22.5], "uv": [147, 156]},
						{"origin": [-6.56974, 16.41147, -19.53627], "size": [1.26957, 1.1152, 8.07274], "inflate": -0.5, "pivot": [-6.06974, 16.91147, -17.96798], "rotation": [0, 0, -22.5], "uv": [147, 156]},
						{"origin": [-6.36477, 15.26585, -19.53627], "size": [1.26957, 1.1152, 8.07274], "inflate": -0.5, "uv": [147, 156]},
						{"origin": [-6.61382, 15.369, -19.53627], "size": [1.26957, 1.1152, 8.07274], "inflate": -0.5, "pivot": [-6.11382, 15.869, -17.96798], "rotation": [0, 0, 22.5], "uv": [147, 156]},
						{"origin": [-6.80444, 15.55962, -19.53627], "size": [1.26957, 1.1152, 8.07274], "inflate": -0.5, "pivot": [-6.30444, 16.05962, -17.96798], "rotation": [0, 0, 45], "uv": [147, 156]},
						{"origin": [-6.9076, 15.80867, -19.53627], "size": [1.26957, 1.1152, 8.07274], "inflate": -0.5, "pivot": [-6.4076, 16.30867, -17.96798], "rotation": [0, 0, 67.5], "uv": [147, 156]}
					]
				},
				{
					"name": "cover2",
					"parent": "hole",
					"pivot": [-5.24463, 10.36378, -7.44268]
				},
				{
					"name": "hole3",
					"parent": "barrel",
					"pivot": [-5.73025, 17.30843, -21.67073],
					"cubes": [
						{"origin": [-6.34983, 16.45275, -26.10162], "size": [1.23962, 1.1024, 10.33729], "inflate": -0.5, "uv": [0, 154]},
						{"origin": [-9.44109, 15.90056, -26.10162], "size": [1.23962, 1.1024, 10.33729], "inflate": -0.5, "pivot": [-5.88763, 8.40632, -13.22273], "rotation": [0, 0, 22.5], "uv": [0, 154]},
						{"origin": [-11.45863, 14.03911, -26.10162], "size": [1.23962, 1.1024, 10.33729], "inflate": -0.5, "pivot": [-5.3709, 9.07914, -13.22273], "rotation": [0, 0, 45], "uv": [0, 154]},
						{"origin": [-14.30776, 14.46297, -26.10162], "size": [1.23962, 1.1024, 10.33729], "inflate": -0.5, "pivot": [-8.22003, 9.503, -13.22273], "rotation": [0, 0, 67.5], "uv": [0, 154]},
						{"origin": [-5.7301, 16.07265, -26.10162], "size": [1.23962, 1.1024, 10.33729], "inflate": -0.5, "pivot": [-5.2301, 16.57265, -24.60162], "rotation": [0, 0, 90], "uv": [0, 154]},
						{"origin": [-6.83234, 16.07265, -26.10162], "size": [1.23962, 1.1024, 10.33729], "inflate": -0.5, "pivot": [-6.33234, 16.57265, -24.60162], "rotation": [0, 0, 90], "uv": [0, 154]},
						{"origin": [-5.7194, 15.61165, -26.10162], "size": [1.23962, 1.1024, 10.33729], "inflate": -0.5, "pivot": [-5.2194, 16.11165, -24.60162], "rotation": [0, 0, -67.5], "uv": [0, 154]},
						{"origin": [-6.73773, 16.03346, -26.10162], "size": [1.23962, 1.1024, 10.33729], "inflate": -0.5, "pivot": [-6.23773, 16.53346, -24.60162], "rotation": [0, 0, -67.5], "uv": [0, 154]},
						{"origin": [-5.88884, 15.44222, -26.10162], "size": [1.23962, 1.1024, 10.33729], "inflate": -0.5, "pivot": [-5.38884, 15.94222, -24.60162], "rotation": [0, 0, -45], "uv": [0, 154]},
						{"origin": [-6.66823, 16.22161, -26.10162], "size": [1.23962, 1.1024, 10.33729], "inflate": -0.5, "pivot": [-6.16823, 16.72161, -24.60162], "rotation": [0, 0, -45], "uv": [0, 154]},
						{"origin": [-6.11021, 15.35052, -26.10162], "size": [1.23962, 1.1024, 10.33729], "inflate": -0.5, "pivot": [-5.61021, 15.85052, -24.60162], "rotation": [0, 0, -22.5], "uv": [0, 154]},
						{"origin": [-6.53202, 16.36885, -26.10162], "size": [1.23962, 1.1024, 10.33729], "inflate": -0.5, "pivot": [-6.03202, 16.86885, -24.60162], "rotation": [0, 0, -22.5], "uv": [0, 154]},
						{"origin": [-6.34983, 15.35052, -26.10162], "size": [1.23962, 1.1024, 10.33729], "inflate": -0.5, "uv": [0, 154]},
						{"origin": [-6.5712, 15.44222, -26.10162], "size": [1.23962, 1.1024, 10.33729], "inflate": -0.5, "pivot": [-6.0712, 15.94222, -24.60162], "rotation": [0, 0, 22.5], "uv": [0, 154]},
						{"origin": [-6.74064, 15.61165, -26.10162], "size": [1.23962, 1.1024, 10.33729], "inflate": -0.5, "pivot": [-6.24064, 16.11165, -24.60162], "rotation": [0, 0, 45], "uv": [0, 154]},
						{"origin": [-6.83234, 15.83303, -26.10162], "size": [1.23962, 1.1024, 10.33729], "inflate": -0.5, "pivot": [-6.33234, 16.33303, -24.60162], "rotation": [0, 0, 67.5], "uv": [0, 154]}
					]
				},
				{
					"name": "cover4",
					"parent": "hole3",
					"pivot": [-4.66189, 9.14288, -12.21571]
				},
				{
					"name": "shell",
					"parent": "barrel",
					"pivot": [-5.73025, 17.30843, -1.67073],
					"cubes": [
						{"origin": [-6.31864, 16.54551, -5.07644], "size": [1.17713, 1.07569, 3.2], "inflate": -0.5, "uv": [104, 149]},
						{"origin": [-8.6037, 16.13733, -5.07644], "size": [1.17713, 1.07569, 3.2], "inflate": -0.5, "pivot": [-5.84659, 10.72799, 4.57403], "rotation": [0, 0, 22.5], "uv": [104, 149]},
						{"origin": [-10.09507, 14.76135, -5.07644], "size": [1.17713, 1.07569, 3.2], "inflate": -0.5, "pivot": [-5.46462, 11.22534, 4.57403], "rotation": [0, 0, 45], "uv": [104, 149]},
						{"origin": [-12.20115, 15.07467, -5.07644], "size": [1.17713, 1.07569, 3.2], "inflate": -0.5, "pivot": [-7.5707, 11.53866, 4.57403], "rotation": [0, 0, 67.5], "uv": [104, 149]},
						{"origin": [-5.86054, 16.26454, -5.07644], "size": [1.17713, 1.07569, 3.2], "inflate": -0.5, "pivot": [-5.36054, 16.76454, -3.83724], "rotation": [0, 0, 90], "uv": [104, 149]},
						{"origin": [-6.67531, 16.26454, -5.07644], "size": [1.17713, 1.07569, 3.2], "inflate": -0.5, "pivot": [-6.17531, 16.76454, -3.83724], "rotation": [0, 0, 90], "uv": [104, 149]},
						{"origin": [-5.85263, 15.92377, -5.07644], "size": [1.17713, 1.07569, 3.2], "inflate": -0.5, "pivot": [-5.35263, 16.42377, -3.83724], "rotation": [0, 0, -67.5], "uv": [104, 149]},
						{"origin": [-6.60538, 16.23557, -5.07644], "size": [1.17713, 1.07569, 3.2], "inflate": -0.5, "pivot": [-6.10538, 16.73557, -3.83724], "rotation": [0, 0, -67.5], "uv": [104, 149]},
						{"origin": [-5.97788, 15.79853, -5.07644], "size": [1.17713, 1.07569, 3.2], "inflate": -0.5, "pivot": [-5.47788, 16.29853, -3.83724], "rotation": [0, 0, -45], "uv": [104, 149]},
						{"origin": [-6.554, 16.37465, -5.07644], "size": [1.17713, 1.07569, 3.2], "inflate": -0.5, "pivot": [-6.054, 16.87465, -3.83724], "rotation": [0, 0, -45], "uv": [104, 149]},
						{"origin": [-6.14152, 15.73074, -5.07644], "size": [1.17713, 1.07569, 3.2], "inflate": -0.5, "pivot": [-5.64152, 16.23074, -3.83724], "rotation": [0, 0, -22.5], "uv": [104, 149]},
						{"origin": [-6.45332, 16.48349, -5.07644], "size": [1.17713, 1.07569, 3.2], "inflate": -0.5, "pivot": [-5.95332, 16.98349, -3.83724], "rotation": [0, 0, -22.5], "uv": [104, 149]},
						{"origin": [-6.31864, 15.73074, -5.07644], "size": [1.17713, 1.07569, 3.2], "inflate": -0.5, "uv": [104, 149]},
						{"origin": [-6.48228, 15.79853, -5.07644], "size": [1.17713, 1.07569, 3.2], "inflate": -0.5, "pivot": [-5.98228, 16.29853, -3.83724], "rotation": [0, 0, 22.5], "uv": [104, 149]},
						{"origin": [-6.60753, 15.92377, -5.07644], "size": [1.17713, 1.07569, 3.2], "inflate": -0.5, "pivot": [-6.10753, 16.42377, -3.83724], "rotation": [0, 0, 45], "uv": [104, 149]},
						{"origin": [-6.67531, 16.08741, -5.07644], "size": [1.17713, 1.07569, 3.2], "inflate": -0.5, "pivot": [-6.17531, 16.58741, -3.83724], "rotation": [0, 0, 67.5], "uv": [104, 149]}
					]
				},
				{
					"name": "cover13",
					"parent": "shell",
					"pivot": [-3.44607, 5.45442, 7.84055]
				},
				{
					"name": "hole14",
					"parent": "shell",
					"pivot": [-5.73025, 16.6, -1.67073],
					"cubes": [
						{"origin": [-6.32041, 16.55442, -3.09456], "size": [1.18067, 1.07721, 1.612], "inflate": -0.5, "uv": [80, 142]},
						{"origin": [-8.65117, 16.13808, -3.09456], "size": [1.18067, 1.07721, 1.612], "inflate": -0.5, "pivot": [-5.84891, 10.61055, 5.71893], "rotation": [0, 0, 22.5], "uv": [80, 142]},
						{"origin": [-10.17236, 14.73458, -3.09456], "size": [1.18067, 1.07721, 1.612], "inflate": -0.5, "pivot": [-5.45931, 11.11785, 5.71893], "rotation": [0, 0, 45], "uv": [80, 142]},
						{"origin": [-12.32056, 15.05416, -3.09456], "size": [1.18067, 1.07721, 1.612], "inflate": -0.5, "pivot": [-7.6075, 11.43743, 5.71893], "rotation": [0, 0, 67.5], "uv": [80, 142]},
						{"origin": [-5.85314, 16.26783, -3.09456], "size": [1.18067, 1.07721, 1.612], "inflate": -0.5, "pivot": [-5.35314, 16.76783, -2.86057], "rotation": [0, 0, 90], "uv": [80, 142]},
						{"origin": [-6.68422, 16.26783, -3.09456], "size": [1.18067, 1.07721, 1.612], "inflate": -0.5, "pivot": [-6.18422, 16.76783, -2.86057], "rotation": [0, 0, 90], "uv": [80, 142]},
						{"origin": [-5.84508, 15.92025, -3.09456], "size": [1.18067, 1.07721, 1.612], "inflate": -0.5, "pivot": [-5.34508, 16.42025, -2.86057], "rotation": [0, 0, -67.5], "uv": [80, 142]},
						{"origin": [-6.61288, 16.23828, -3.09456], "size": [1.18067, 1.07721, 1.612], "inflate": -0.5, "pivot": [-6.11288, 16.73828, -2.86057], "rotation": [0, 0, -67.5], "uv": [80, 142]},
						{"origin": [-5.97283, 15.7925, -3.09456], "size": [1.18067, 1.07721, 1.612], "inflate": -0.5, "pivot": [-5.47283, 16.2925, -2.86057], "rotation": [0, 0, -45], "uv": [80, 142]},
						{"origin": [-6.56048, 16.38015, -3.09456], "size": [1.18067, 1.07721, 1.612], "inflate": -0.5, "pivot": [-6.06048, 16.88015, -2.86057], "rotation": [0, 0, -45], "uv": [80, 142]},
						{"origin": [-6.13974, 15.72336, -3.09456], "size": [1.18067, 1.07721, 1.612], "inflate": -0.5, "pivot": [-5.63974, 16.22336, -2.86057], "rotation": [0, 0, -22.5], "uv": [80, 142]},
						{"origin": [-6.45778, 16.49116, -3.09456], "size": [1.18067, 1.07721, 1.612], "inflate": -0.5, "pivot": [-5.95778, 16.99116, -2.86057], "rotation": [0, 0, -22.5], "uv": [80, 142]},
						{"origin": [-6.32041, 15.72336, -3.09456], "size": [1.18067, 1.07721, 1.612], "inflate": -0.5, "uv": [80, 142]},
						{"origin": [-6.48732, 15.7925, -3.09456], "size": [1.18067, 1.07721, 1.612], "inflate": -0.5, "pivot": [-5.98732, 16.2925, -2.86057], "rotation": [0, 0, 22.5], "uv": [80, 142]},
						{"origin": [-6.61508, 15.92025, -3.09456], "size": [1.18067, 1.07721, 1.612], "inflate": -0.5, "pivot": [-6.11508, 16.42025, -2.86057], "rotation": [0, 0, 45], "uv": [80, 142]},
						{"origin": [-6.68422, 16.08716, -3.09456], "size": [1.18067, 1.07721, 1.612], "inflate": -0.5, "pivot": [-6.18422, 16.58716, -2.86057], "rotation": [0, 0, 67.5], "uv": [80, 142]}
					]
				},
				{
					"name": "cover14",
					"parent": "hole14",
					"pivot": [-3.51499, 5.66351, 8.99736]
				},
				{
					"name": "hole16",
					"parent": "shell",
					"pivot": [-5.73025, 16.6, -3.67073],
					"cubes": [
						{"origin": [-6.31861, 16.54533, -5.4], "size": [1.17706, 1.07566, 1.59976], "inflate": -0.5, "uv": [103, 145]},
						{"origin": [-8.60275, 16.13732, -5.4], "size": [1.17706, 1.07566, 1.59976], "inflate": -0.5, "pivot": [-5.84654, 10.73034, 3.57113], "rotation": [0, 0, 22.5], "uv": [103, 145]},
						{"origin": [-10.09352, 14.76188, -5.4], "size": [1.17706, 1.07566, 1.59976], "inflate": -0.5, "pivot": [-5.46472, 11.22749, 3.57113], "rotation": [0, 0, 45], "uv": [103, 145]},
						{"origin": [-12.19876, 15.07508, -5.4], "size": [1.17706, 1.07566, 1.59976], "inflate": -0.5, "pivot": [-7.56996, 11.54068, 3.57113], "rotation": [0, 0, 67.5], "uv": [103, 145]},
						{"origin": [-5.86069, 16.26448, -5.4], "size": [1.17706, 1.07566, 1.59976], "inflate": -0.5, "pivot": [-5.36069, 16.76448, -4.83678], "rotation": [0, 0, 90], "uv": [103, 145]},
						{"origin": [-6.67514, 16.26448, -5.4], "size": [1.17706, 1.07566, 1.59976], "inflate": -0.5, "pivot": [-6.17514, 16.76448, -4.83678], "rotation": [0, 0, 90], "uv": [103, 145]},
						{"origin": [-5.85278, 15.92384, -5.4], "size": [1.17706, 1.07566, 1.59976], "inflate": -0.5, "pivot": [-5.35278, 16.42384, -4.83678], "rotation": [0, 0, -67.5], "uv": [103, 145]},
						{"origin": [-6.60523, 16.23552, -5.4], "size": [1.17706, 1.07566, 1.59976], "inflate": -0.5, "pivot": [-6.10523, 16.73552, -4.83678], "rotation": [0, 0, -67.5], "uv": [103, 145]},
						{"origin": [-5.97798, 15.79865, -5.4], "size": [1.17706, 1.07566, 1.59976], "inflate": -0.5, "pivot": [-5.47798, 16.29865, -4.83678], "rotation": [0, 0, -45], "uv": [103, 145]},
						{"origin": [-6.55388, 16.37454, -5.4], "size": [1.17706, 1.07566, 1.59976], "inflate": -0.5, "pivot": [-6.05388, 16.87454, -4.83678], "rotation": [0, 0, -45], "uv": [103, 145]},
						{"origin": [-6.14155, 15.73089, -5.4], "size": [1.17706, 1.07566, 1.59976], "inflate": -0.5, "pivot": [-5.64155, 16.23089, -4.83678], "rotation": [0, 0, -22.5], "uv": [103, 145]},
						{"origin": [-6.45323, 16.48334, -5.4], "size": [1.17706, 1.07566, 1.59976], "inflate": -0.5, "pivot": [-5.95323, 16.98334, -4.83678], "rotation": [0, 0, -22.5], "uv": [103, 145]},
						{"origin": [-6.31861, 15.73089, -5.4], "size": [1.17706, 1.07566, 1.59976], "inflate": -0.5, "uv": [103, 145]},
						{"origin": [-6.48218, 15.79865, -5.4], "size": [1.17706, 1.07566, 1.59976], "inflate": -0.5, "pivot": [-5.98218, 16.29865, -4.83678], "rotation": [0, 0, 22.5], "uv": [103, 145]},
						{"origin": [-6.60738, 15.92384, -5.4], "size": [1.17706, 1.07566, 1.59976], "inflate": -0.5, "pivot": [-6.10738, 16.42384, -4.83678], "rotation": [0, 0, 45], "uv": [103, 145]},
						{"origin": [-6.67514, 16.08742, -5.4], "size": [1.17706, 1.07566, 1.59976], "inflate": -0.5, "pivot": [-6.17514, 16.58742, -4.83678], "rotation": [0, 0, 67.5], "uv": [103, 145]}
					]
				},
				{
					"name": "cover16",
					"parent": "hole16",
					"pivot": [-3.44469, 5.45024, 6.87741]
				},
				{
					"name": "hole15",
					"parent": "shell",
					"pivot": [-5.73025, 16.6, -1.67073],
					"cubes": [
						{"origin": [-6.32773, 16.59132, -2.55], "size": [1.19534, 1.08348, 1.102], "inflate": -0.5, "uv": [80, 142]},
						{"origin": [-8.84775, 16.14117, -2.55], "size": [1.19534, 1.08348, 1.102], "inflate": -0.5, "pivot": [-5.85855, 10.12421, 6.31897], "rotation": [0, 0, 22.5], "uv": [80, 142]},
						{"origin": [-10.49246, 14.6237, -2.55], "size": [1.19534, 1.08348, 1.102], "inflate": -0.5, "pivot": [-5.43731, 10.67269, 6.31897], "rotation": [0, 0, 45], "uv": [80, 142]},
						{"origin": [-12.8151, 14.96924, -2.55], "size": [1.19534, 1.08348, 1.102], "inflate": -0.5, "pivot": [-7.75994, 11.01823, 6.31897], "rotation": [0, 0, 67.5], "uv": [80, 142]},
						{"origin": [-5.82252, 16.28146, -2.55], "size": [1.19534, 1.08348, 1.102], "inflate": -0.5, "pivot": [-5.32252, 16.78146, -2.95719], "rotation": [0, 0, 90], "uv": [80, 142]},
						{"origin": [-6.72108, 16.28146, -2.55], "size": [1.19534, 1.95, 1.102], "inflate": -0.5, "pivot": [-6.22108, 16.78146, -2.95719], "rotation": [0, 0, 90], "uv": [80, 142]},
						{"origin": [-5.8138, 15.90565, -2.55], "size": [1.19534, 1.95, 1.102], "inflate": -0.5, "pivot": [-5.3138, 16.40565, -2.95719], "rotation": [0, 0, -67.5], "uv": [80, 142]},
						{"origin": [-6.64395, 16.24951, -2.55], "size": [1.19534, 1.08348, 1.102], "inflate": -0.5, "pivot": [-6.14395, 16.74951, -2.95719], "rotation": [0, 0, -67.5], "uv": [80, 142]},
						{"origin": [-5.95193, 15.76753, -2.55], "size": [1.19534, 1.95, 1.102], "inflate": -0.5, "pivot": [-5.45193, 16.26753, -2.95719], "rotation": [0, 0, -45], "uv": [80, 142]},
						{"origin": [-6.58729, 16.40289, -2.55], "size": [1.19534, 1.08348, 1.102], "inflate": -0.5, "pivot": [-6.08729, 16.90289, -2.95719], "rotation": [0, 0, -45], "uv": [80, 142]},
						{"origin": [-6.13239, 15.69277, -2.55], "size": [1.19534, 1.95, 1.102], "inflate": -0.5, "pivot": [-5.63239, 16.19277, -2.95719], "rotation": [0, 0, -22.5], "uv": [80, 142]},
						{"origin": [-6.47626, 16.52292, -2.55], "size": [1.19534, 1.08348, 1.102], "inflate": -0.5, "pivot": [-5.97626, 17.02292, -2.95719], "rotation": [0, 0, -22.5], "uv": [80, 142]},
						{"origin": [-6.32773, 15.69277, -2.55], "size": [1.19534, 1.95, 1.102], "inflate": -0.5, "uv": [80, 142]},
						{"origin": [-6.50819, 15.76753, -2.55], "size": [1.19534, 1.95, 1.102], "inflate": -0.5, "pivot": [-6.00819, 16.26753, -2.95719], "rotation": [0, 0, 22.5], "uv": [80, 142]},
						{"origin": [-6.64632, 15.90565, -2.55], "size": [1.19534, 1.95, 1.102], "inflate": -0.5, "pivot": [-6.14632, 16.40565, -2.95719], "rotation": [0, 0, 45], "uv": [80, 142]},
						{"origin": [-6.72108, 16.08612, -2.55], "size": [1.19534, 1.95, 1.102], "inflate": -0.5, "pivot": [-6.22108, 16.58612, -2.95719], "rotation": [0, 0, 67.5], "uv": [80, 142]}
					]
				},
				{
					"name": "cover15",
					"parent": "hole15",
					"pivot": [-3.80041, 6.52938, 9.64674]
				},
				{
					"name": "hole11",
					"parent": "barrel",
					"pivot": [-5.73025, 18.08892, -16.69512],
					"cubes": [
						{"origin": [-6.29004, 17.41108, -19.16057], "size": [1.11981, 1.0512, 5.66864], "inflate": -0.5, "uv": [153, 159]},
						{"origin": [-7.83567, 17.13498, -19.16057], "size": [1.11981, 1.0512, 5.66864], "inflate": -0.5, "pivot": [-5.80894, 13.63786, -12.47112], "rotation": [0, 0, 22.5], "uv": [153, 159]},
						{"origin": [-8.84444, 16.20426, -19.16057], "size": [1.11981, 1.0512, 5.66864], "inflate": -0.5, "pivot": [-5.55057, 13.97427, -12.47112], "rotation": [0, 0, 45], "uv": [153, 159]},
						{"origin": [-10.26901, 16.41619, -19.16057], "size": [1.11981, 1.0512, 5.66864], "inflate": -0.5, "pivot": [-6.97514, 14.1862, -12.47112], "rotation": [0, 0, 67.5], "uv": [153, 159]},
						{"origin": [-5.98018, 17.22103, -19.16057], "size": [1.11981, 1.0512, 5.66864], "inflate": -0.5, "pivot": [-5.48018, 17.72103, -18.16057], "rotation": [0, 0, 90], "uv": [153, 159]},
						{"origin": [-6.53129, 17.22103, -19.16057], "size": [1.11981, 1.0512, 5.66864], "inflate": -0.5, "pivot": [-6.03129, 17.72103, -18.16057], "rotation": [0, 0, 90], "uv": [153, 159]},
						{"origin": [-5.97483, 16.99053, -19.16057], "size": [1.11981, 1.0512, 5.66864], "inflate": -0.5, "pivot": [-5.47483, 17.49053, -18.16057], "rotation": [0, 0, -67.5], "uv": [153, 159]},
						{"origin": [-6.48399, 17.20143, -19.16057], "size": [1.11981, 1.0512, 5.66864], "inflate": -0.5, "pivot": [-5.98399, 17.70143, -18.16057], "rotation": [0, 0, -67.5], "uv": [153, 159]},
						{"origin": [-6.05954, 16.90581, -19.16057], "size": [1.11981, 1.0512, 5.66864], "inflate": -0.5, "pivot": [-5.55954, 17.40581, -18.16057], "rotation": [0, 0, -45], "uv": [153, 159]},
						{"origin": [-6.44924, 17.29551, -19.16057], "size": [1.11981, 1.0512, 5.66864], "inflate": -0.5, "pivot": [-5.94924, 17.79551, -18.16057], "rotation": [0, 0, -45], "uv": [153, 159]},
						{"origin": [-6.17023, 16.85996, -19.16057], "size": [1.11981, 1.0512, 5.66864], "inflate": -0.5, "pivot": [-5.67023, 17.35996, -18.16057], "rotation": [0, 0, -22.5], "uv": [153, 159]},
						{"origin": [-6.38113, 17.36913, -19.16057], "size": [1.11981, 1.0512, 5.66864], "inflate": -0.5, "pivot": [-5.88113, 17.86913, -18.16057], "rotation": [0, 0, -22.5], "uv": [153, 159]},
						{"origin": [-6.29004, 16.85996, -19.16057], "size": [1.11981, 1.0512, 5.66864], "inflate": -0.5, "uv": [153, 159]},
						{"origin": [-6.40073, 16.90581, -19.16057], "size": [1.11981, 1.0512, 5.66864], "inflate": -0.5, "pivot": [-5.90073, 17.40581, -18.16057], "rotation": [0, 0, 22.5], "uv": [153, 159]},
						{"origin": [-6.48544, 16.99053, -19.16057], "size": [1.11981, 1.0512, 5.66864], "inflate": -0.5, "pivot": [-5.98544, 17.49053, -18.16057], "rotation": [0, 0, 45], "uv": [153, 159]},
						{"origin": [-6.53129, 17.10122, -19.16057], "size": [1.11981, 1.0512, 5.66864], "inflate": -0.5, "pivot": [-6.03129, 17.60122, -18.16057], "rotation": [0, 0, 67.5], "uv": [153, 159]}
					]
				},
				{
					"name": "cover11",
					"parent": "hole11",
					"pivot": [-2.33095, 4.76656, -1.13225]
				},
				{
					"name": "hole7",
					"parent": "barrel",
					"pivot": [-5.73025, 22.77184, 2.32927],
					"rotation": [0, 90, 0],
					"cubes": [
						{"origin": [-6.204, 21.18786, 1.31203], "size": [1.19169, 1.56972, 1.23083], "inflate": -0.5, "uv": [0, 163]},
						{"origin": [-10.2754, 19.90367, 1.31203], "size": [1.19169, 1.66729, 1.23083], "inflate": -0.5, "pivot": [-4.66107, 10.94827, 8.59319], "rotation": [0, 0, 22.5], "uv": [0, 163]},
						{"origin": [-13.08109, 17.0171, 1.31203], "size": [1.19169, 1.76485, 1.23083], "inflate": -0.5, "pivot": [-4.24769, 11.48653, 8.59319], "rotation": [0, 0, 45], "uv": [0, 163]},
						{"origin": [-15.96392, 15.79682, 1.31203], "size": [1.19169, 1.66729, 1.23083], "inflate": -0.5, "pivot": [-6.52699, 11.82562, 8.59319], "rotation": [0, 0, 67.5], "uv": [0, 163]},
						{"origin": [-9.02529, 15.12767, 1.31203], "size": [1.19169, 1.86241, 1.23083], "inflate": -0.5, "pivot": [-4.13505, 17.48133, -0.50992], "rotation": [0, 0, 90], "uv": [0, 163]},
						{"origin": [-9.90708, 15.90816, 1.31203], "size": [1.19169, 1.86241, 1.23083], "inflate": -0.5, "pivot": [-5.01684, 17.48133, -0.50992], "rotation": [0, 0, 90], "uv": [0, 163]},
						{"origin": [-0.98112, 19.28409, 1.31203], "size": [1.19169, 1.86241, 1.23083], "inflate": -0.5, "pivot": [-4.12649, 17.11254, -0.50992], "rotation": [0, 0, -67.5], "uv": [0, 163]},
						{"origin": [-1.79578, 18.84105, 1.31203], "size": [1.19169, 1.86241, 1.23083], "inflate": -0.5, "pivot": [-4.94115, 17.44998, -0.50992], "rotation": [0, 0, -67.5], "uv": [0, 163]},
						{"origin": [-2.41651, 20.34021, 1.31203], "size": [1.19169, 1.08192, 1.23083], "inflate": -0.5, "pivot": [-4.26204, 16.97699, -0.50992], "rotation": [0, 0, -45], "uv": [0, 163]},
						{"origin": [-3.04003, 20.2808, 1.31203], "size": [1.19169, 1.76485, 1.23083], "inflate": -0.5, "pivot": [-4.88555, 17.60051, -0.50992], "rotation": [0, 0, -45], "uv": [0, 163]},
						{"origin": [-4.25054, 20.87037, 1.31203], "size": [1.19169, 1.08192, 1.23083], "inflate": -0.5, "pivot": [-4.43914, 16.90363, -0.50992], "rotation": [0, 0, -22.5], "uv": [0, 163]},
						{"origin": [-4.58799, 21.39235, 1.31203], "size": [1.19169, 1.3746, 1.23083], "inflate": -0.5, "pivot": [-4.77658, 17.7183, -0.50992], "rotation": [0, 0, -22.5], "uv": [0, 163]},
						{"origin": [-6.204, 20.79388, 1.31203], "size": [1.19169, 1.08192, 1.23083], "inflate": -0.5, "uv": [0, 163]},
						{"origin": [-7.97948, 20.12236, 1.31203], "size": [1.19169, 1.08192, 1.23083], "inflate": -0.5, "pivot": [-4.80793, 16.97699, -0.50992], "rotation": [0, 0, 22.5], "uv": [0, 163]},
						{"origin": [-9.3067, 18.95806, 1.31203], "size": [1.19169, 1.08192, 1.23083], "inflate": -0.5, "pivot": [-4.94348, 17.11254, -0.50992], "rotation": [0, 0, 45], "uv": [0, 163]},
						{"origin": [-9.98358, 17.47823, 1.31203], "size": [1.19169, 1.08192, 1.23083], "inflate": -0.5, "pivot": [-5.01684, 17.28964, -0.50992], "rotation": [0, 0, 67.5], "uv": [0, 163]}
					]
				},
				{
					"name": "cover7",
					"parent": "hole7",
					"pivot": [-4.66189, 14.60629, 11.78429]
				},
				{
					"name": "hole12",
					"parent": "barrel",
					"pivot": [-4.75464, 17.99136, -7.52439],
					"rotation": [-90, 90, 0],
					"cubes": [
						{"origin": [-5.18, 15.1, -8.5], "size": [1.4, 2, 1.7], "inflate": -0.5, "pivot": [-4.15944, 16.70084, -8], "rotation": [0, 0, 90], "uv": [0, 163]},
						{"origin": [-5.4, 16.32, -8.5], "size": [1.44, 1.4, 1.2], "inflate": -0.5, "pivot": [-4.15944, 16.70084, -8], "rotation": [0, -45, 0], "uv": [0, 163]},
						{"origin": [-5.04, 16.32, -8.55], "size": [2.44, 1.4, 1.2], "inflate": -0.5, "pivot": [-4.15944, 16.70084, -8], "rotation": [0, -37.5, 0], "uv": [0, 163]},
						{"origin": [-5.5, 16.32, -8.35], "size": [1.2, 1.4, 1.2], "inflate": -0.5, "pivot": [-4.15944, 16.70084, -8], "rotation": [0, -57.5, 0], "uv": [0, 163]},
						{"origin": [-5.41665, 16.32, -9.90904], "size": [1.3, 1.4, 1.2], "inflate": -0.5, "pivot": [-5.15944, 17, -9], "rotation": [0, -85, 0], "uv": [0, 163]},
						{"origin": [-5.8, 16.32, -9.98], "size": [1.3, 1.4, 1.2], "inflate": -0.5, "pivot": [-5.15944, 17, -9], "rotation": [0, -105, 0], "uv": [0, 163]},
						{"origin": [-6.05, 16.32, -9.97], "size": [1.3, 1.4, 1.2], "inflate": -0.5, "pivot": [-5.15944, 17, -9], "rotation": [0, -120, 0], "uv": [0, 163]},
						{"origin": [-6.1, 16.32, -9.9], "size": [1.5, 1.4, 1.2], "inflate": -0.5, "pivot": [-5.15944, 17, -9], "rotation": [0, -127.5, 0], "uv": [0, 163]},
						{"origin": [-5.58, 16.32, -9.89], "size": [1.3, 1.4, 1.2], "inflate": -0.5, "pivot": [-5.15944, 17, -9], "rotation": [0, -117.5, 0], "uv": [0, 163]},
						{"origin": [-5.25, 16.32, -9.79], "size": [1.3, 1.4, 1.2], "inflate": -0.5, "pivot": [-5.15944, 17, -9], "rotation": [0, -102.5, 0], "uv": [0, 163]},
						{"origin": [-4.95, 16.32, -9.73], "size": [1.3, 1.4, 1.2], "inflate": -0.5, "pivot": [-5.15944, 17, -9], "rotation": [0, -97.5, 0], "uv": [0, 163]}
					]
				},
				{
					"name": "cover12",
					"parent": "hole12",
					"pivot": [-3.68628, 9.8258, 1.93063]
				},
				{
					"name": "hole9",
					"parent": "barrel",
					"pivot": [-5.73025, 22.77184, -18.54878],
					"rotation": [0, 90, 0],
					"cubes": [
						{"origin": [-7.03676, 20.5731, -19.56602], "size": [1.19169, 1.56972, 1.23083], "inflate": -0.5, "uv": [3, 163]},
						{"origin": [-11.10816, 19.28891, -19.56602], "size": [1.19169, 1.66729, 1.23083], "inflate": -0.5, "pivot": [-5.49383, 10.33351, -12.28486], "rotation": [0, 0, 22.5], "uv": [3, 163]},
						{"origin": [-13.91385, 16.40234, -19.56602], "size": [1.19169, 1.76485, 1.23083], "inflate": -0.5, "pivot": [-5.08045, 10.87177, -12.28486], "rotation": [0, 0, 45], "uv": [3, 163]},
						{"origin": [-16.79668, 15.18206, -19.56602], "size": [1.19169, 1.66729, 1.23083], "inflate": -0.5, "pivot": [-7.35975, 11.21085, -12.28486], "rotation": [0, 0, 67.5], "uv": [3, 163]},
						{"origin": [-9.85805, 14.51291, -19.56602], "size": [1.19169, 1.86241, 1.23083], "inflate": -0.5, "pivot": [-4.96781, 16.86657, -21.38797], "rotation": [0, 0, 90], "uv": [3, 163]},
						{"origin": [-10.73984, 15.2934, -19.56602], "size": [1.19169, 1.86241, 1.23083], "inflate": -0.5, "pivot": [-5.8496, 16.86657, -21.38797], "rotation": [0, 0, 90], "uv": [3, 163]},
						{"origin": [-1.81388, 18.66933, -19.56602], "size": [1.19169, 1.86241, 1.23083], "inflate": -0.5, "pivot": [-4.95925, 16.49778, -21.38797], "rotation": [0, 0, -67.5], "uv": [3, 163]},
						{"origin": [-2.62854, 18.22629, -19.56602], "size": [1.19169, 1.86241, 1.23083], "inflate": -0.5, "pivot": [-5.77391, 16.83522, -21.38797], "rotation": [0, 0, -67.5], "uv": [3, 163]},
						{"origin": [-3.24927, 19.72545, -19.56602], "size": [1.19169, 1.08192, 1.23083], "inflate": -0.5, "pivot": [-5.0948, 16.36223, -21.38797], "rotation": [0, 0, -45], "uv": [3, 163]},
						{"origin": [-3.87279, 19.66604, -19.56602], "size": [1.19169, 1.76485, 1.23083], "inflate": -0.5, "pivot": [-5.71831, 16.98575, -21.38797], "rotation": [0, 0, -45], "uv": [3, 163]},
						{"origin": [-5.0833, 20.25561, -19.56602], "size": [1.19169, 1.08192, 1.23083], "inflate": -0.5, "pivot": [-5.2719, 16.28887, -21.38797], "rotation": [0, 0, -22.5], "uv": [3, 163]},
						{"origin": [-5.42075, 20.77759, -19.56602], "size": [1.19169, 1.3746, 1.23083], "inflate": -0.5, "pivot": [-5.60934, 17.10353, -21.38797], "rotation": [0, 0, -22.5], "uv": [3, 163]},
						{"origin": [-7.03676, 20.17912, -19.56602], "size": [1.19169, 1.08192, 1.23083], "inflate": -0.5, "uv": [3, 163]},
						{"origin": [-8.81224, 19.5076, -19.56602], "size": [1.19169, 1.08192, 1.23083], "inflate": -0.5, "pivot": [-5.64069, 16.36223, -21.38797], "rotation": [0, 0, 22.5], "uv": [3, 163]},
						{"origin": [-10.13946, 18.3433, -19.56602], "size": [1.19169, 1.08192, 1.23083], "inflate": -0.5, "pivot": [-5.77624, 16.49778, -21.38797], "rotation": [0, 0, 45], "uv": [3, 163]},
						{"origin": [-10.81634, 16.86347, -19.56602], "size": [1.19169, 1.08192, 1.23083], "inflate": -0.5, "pivot": [-5.8496, 16.67488, -21.38797], "rotation": [0, 0, 67.5], "uv": [3, 163]}
					]
				},
				{
					"name": "cover9",
					"parent": "hole9",
					"pivot": [-4.66189, 14.60629, -9.09376]
				},
				{
					"name": "hole10",
					"parent": "barrel",
					"pivot": [-4.94976, 22.77184, -18.54878],
					"rotation": [0, 90, 0],
					"cubes": [
						{"origin": [-6.25627, 20.5731, -19.57734], "size": [1.19169, 1.56972, 1.23083], "inflate": -0.5, "uv": [2, 163]},
						{"origin": [-10.32767, 19.28891, -19.57734], "size": [1.19169, 1.66729, 1.23083], "inflate": -0.5, "pivot": [-4.71334, 10.33351, -12.29618], "rotation": [0, 0, 22.5], "uv": [2, 163]},
						{"origin": [-13.13336, 16.40234, -19.57734], "size": [1.19169, 1.76485, 1.23083], "inflate": -0.5, "pivot": [-4.29996, 10.87177, -12.29618], "rotation": [0, 0, 45], "uv": [2, 163]},
						{"origin": [-16.01619, 15.18206, -19.57734], "size": [1.19169, 1.66729, 1.23083], "inflate": -0.5, "pivot": [-6.57926, 11.21085, -12.29618], "rotation": [0, 0, 67.5], "uv": [2, 163]},
						{"origin": [-9.07757, 14.51291, -19.57734], "size": [1.19169, 1.86241, 1.23083], "inflate": -0.5, "pivot": [-4.18732, 16.86657, -21.39929], "rotation": [0, 0, 90], "uv": [2, 163]},
						{"origin": [-9.95935, 15.2934, -19.57734], "size": [1.19169, 1.86241, 1.23083], "inflate": -0.5, "pivot": [-5.06911, 16.86657, -21.39929], "rotation": [0, 0, 90], "uv": [2, 163]},
						{"origin": [-1.03339, 18.66933, -19.57734], "size": [1.19169, 1.86241, 1.23083], "inflate": -0.5, "pivot": [-4.17876, 16.49778, -21.39929], "rotation": [0, 0, -67.5], "uv": [2, 163]},
						{"origin": [-1.84805, 18.22629, -19.57734], "size": [1.19169, 1.86241, 1.23083], "inflate": -0.5, "pivot": [-4.99342, 16.83522, -21.39929], "rotation": [0, 0, -67.5], "uv": [2, 163]},
						{"origin": [-2.46878, 19.72545, -19.57734], "size": [1.19169, 1.08192, 1.23083], "inflate": -0.5, "pivot": [-4.31431, 16.36223, -21.39929], "rotation": [0, 0, -45], "uv": [2, 163]},
						{"origin": [-3.0923, 19.66604, -19.57734], "size": [1.19169, 1.76485, 1.23083], "inflate": -0.5, "pivot": [-4.93782, 16.98575, -21.39929], "rotation": [0, 0, -45], "uv": [2, 163]},
						{"origin": [-4.30282, 20.25561, -19.57734], "size": [1.19169, 1.08192, 1.23083], "inflate": -0.5, "pivot": [-4.49141, 16.28887, -21.39929], "rotation": [0, 0, -22.5], "uv": [2, 163]},
						{"origin": [-4.64026, 20.77759, -19.57734], "size": [1.19169, 1.3746, 1.23083], "inflate": -0.5, "pivot": [-4.82885, 17.10353, -21.39929], "rotation": [0, 0, -22.5], "uv": [2, 163]},
						{"origin": [-6.25627, 20.17912, -19.57734], "size": [1.19169, 1.08192, 1.23083], "inflate": -0.5, "uv": [2, 163]},
						{"origin": [-8.03176, 19.5076, -19.57734], "size": [1.19169, 1.08192, 1.23083], "inflate": -0.5, "pivot": [-4.8602, 16.36223, -21.39929], "rotation": [0, 0, 22.5], "uv": [2, 163]},
						{"origin": [-9.35897, 18.3433, -19.57734], "size": [1.19169, 1.08192, 1.23083], "inflate": -0.5, "pivot": [-4.99575, 16.49778, -21.39929], "rotation": [0, 0, 45], "uv": [2, 163]},
						{"origin": [-10.03585, 16.86347, -19.57734], "size": [1.19169, 1.08192, 1.23083], "inflate": -0.5, "pivot": [-5.06911, 16.67488, -21.39929], "rotation": [0, 0, 67.5], "uv": [2, 163]}
					]
				},
				{
					"name": "cover10",
					"parent": "hole10",
					"pivot": [-3.88141, 14.60629, -9.09376]
				},
				{
					"name": "hole8",
					"parent": "barrel",
					"pivot": [-4.94976, 22.77184, 2.32927],
					"rotation": [0, 90, 0],
					"cubes": [
						{"origin": [-5.42351, 21.18786, 1.31203], "size": [1.19169, 1.56972, 1.23083], "inflate": -0.5, "uv": [0, 163]},
						{"origin": [-9.49491, 19.90367, 1.31203], "size": [1.19169, 1.66729, 1.23083], "inflate": -0.5, "pivot": [-3.88058, 10.94827, 8.59319], "rotation": [0, 0, 22.5], "uv": [0, 163]},
						{"origin": [-12.3006, 17.0171, 1.31203], "size": [1.19169, 1.76485, 1.23083], "inflate": -0.5, "pivot": [-3.4672, 11.48653, 8.59319], "rotation": [0, 0, 45], "uv": [0, 163]},
						{"origin": [-15.18343, 15.79682, 1.31203], "size": [1.19169, 1.66729, 1.23083], "inflate": -0.5, "pivot": [-5.7465, 11.82562, 8.59319], "rotation": [0, 0, 67.5], "uv": [0, 163]},
						{"origin": [-8.24481, 15.12767, 1.31203], "size": [1.19169, 1.86241, 1.23083], "inflate": -0.5, "pivot": [-3.35456, 17.48133, -0.50992], "rotation": [0, 0, 90], "uv": [0, 163]},
						{"origin": [-9.12659, 15.90816, 1.31203], "size": [1.19169, 1.86241, 1.23083], "inflate": -0.5, "pivot": [-4.23635, 17.48133, -0.50992], "rotation": [0, 0, 90], "uv": [0, 163]},
						{"origin": [-0.20063, 19.28409, 1.31203], "size": [1.19169, 1.86241, 1.23083], "inflate": -0.5, "pivot": [-3.346, 17.11254, -0.50992], "rotation": [0, 0, -67.5], "uv": [0, 163]},
						{"origin": [-1.01529, 18.84105, 1.31203], "size": [1.19169, 1.86241, 1.23083], "inflate": -0.5, "pivot": [-4.16066, 17.44998, -0.50992], "rotation": [0, 0, -67.5], "uv": [0, 163]},
						{"origin": [-1.63602, 20.34021, 1.31203], "size": [1.19169, 1.08192, 1.23083], "inflate": -0.5, "pivot": [-3.48155, 16.97699, -0.50992], "rotation": [0, 0, -45], "uv": [0, 163]},
						{"origin": [-2.25954, 20.2808, 1.31203], "size": [1.19169, 1.76485, 1.23083], "inflate": -0.5, "pivot": [-4.10506, 17.60051, -0.50992], "rotation": [0, 0, -45], "uv": [0, 163]},
						{"origin": [-3.47006, 20.87037, 1.31203], "size": [1.19169, 1.08192, 1.23083], "inflate": -0.5, "pivot": [-3.65865, 16.90363, -0.50992], "rotation": [0, 0, -22.5], "uv": [0, 163]},
						{"origin": [-3.8075, 21.39235, 1.31203], "size": [1.19169, 1.3746, 1.23083], "inflate": -0.5, "pivot": [-3.99609, 17.7183, -0.50992], "rotation": [0, 0, -22.5], "uv": [0, 163]},
						{"origin": [-5.42351, 20.79388, 1.31203], "size": [1.19169, 1.08192, 1.23083], "inflate": -0.5, "uv": [0, 163]},
						{"origin": [-7.199, 20.12236, 1.31203], "size": [1.19169, 1.08192, 1.23083], "inflate": -0.5, "pivot": [-4.02744, 16.97699, -0.50992], "rotation": [0, 0, 22.5], "uv": [0, 163]},
						{"origin": [-8.52621, 18.95806, 1.31203], "size": [1.19169, 1.08192, 1.23083], "inflate": -0.5, "pivot": [-4.16299, 17.11254, -0.50992], "rotation": [0, 0, 45], "uv": [0, 163]},
						{"origin": [-9.20309, 17.47823, 1.31203], "size": [1.19169, 1.08192, 1.23083], "inflate": -0.5, "pivot": [-4.23635, 17.28964, -0.50992], "rotation": [0, 0, 67.5], "uv": [0, 163]}
					]
				},
				{
					"name": "cover8",
					"parent": "hole8",
					"pivot": [-3.88141, 14.60629, 11.78429]
				},
				{
					"name": "hole4",
					"parent": "barrel",
					"pivot": [-9.24245, 13.50355, -1.76829],
					"rotation": [0, -90, 0],
					"cubes": [
						{"origin": [-10.34453, 12.26777, -6.19918], "size": [1.23962, 1.1024, 1.84948], "inflate": -0.5, "pivot": [-9.84453, 12.76777, -4.69918], "rotation": [0, 0, 90], "uv": [4, 13]},
						{"origin": [-10.24992, 12.22858, -6.19918], "size": [1.23962, 1.19996, 1.84948], "inflate": -0.5, "pivot": [-9.74992, 12.72858, -4.69918], "rotation": [0, 0, -67.5], "uv": [4, 13]},
						{"origin": [-10.27799, 12.41674, -6.19918], "size": [1.5323, 1.39508, 1.84948], "inflate": -0.5, "pivot": [-9.68043, 12.91674, -4.69918], "rotation": [0, 0, -45], "uv": [4, 13]},
						{"origin": [-10.04421, 12.56397, -6.19918], "size": [2.0201, 1.39508, 1.84948], "inflate": -0.5, "pivot": [-9.54421, 13.06397, -4.69918], "rotation": [0, 0, -22.5], "uv": [4, 13]},
						{"origin": [-10.0834, 11.53978, -6.19918], "size": [1.5323, 1.19996, 1.84948], "inflate": -0.5, "pivot": [-9.5834, 12.13734, -4.69918], "rotation": [0, 0, 22.5], "uv": [4, 13]},
						{"origin": [-10.35039, 11.51409, -6.19918], "size": [1.43474, 1.39508, 1.84948], "inflate": -0.5, "pivot": [-9.75283, 12.30678, -4.69918], "rotation": [0, 0, 45], "uv": [4, 13]},
						{"origin": [-10.34453, 12.02815, -6.19918], "size": [1.23962, 1.1024, 1.84948], "inflate": -0.5, "pivot": [-9.84453, 12.52815, -4.69918], "rotation": [0, 0, 67.5], "uv": [4, 13]}
					]
				},
				{
					"name": "cover3",
					"parent": "hole4",
					"pivot": [-8.17409, 5.338, 7.68673]
				},
				{
					"name": "hole5",
					"parent": "barrel",
					"pivot": [-9.24245, 13.50355, 0.76829],
					"rotation": [0, -90, 0],
					"cubes": [
						{"origin": [-14.12402, 12.09569, -3.76016], "size": [2.70303, 1.78533, 2.0446], "inflate": -0.5, "pivot": [-9.39982, 4.60145, 9.21629], "rotation": [0, 0, 22.5], "uv": [4, 13]},
						{"origin": [-14.97083, 10.23423, -3.76016], "size": [1.23962, 1.98045, 2.0446], "inflate": -0.5, "pivot": [-8.88309, 5.27426, 9.21629], "rotation": [0, 0, 45], "uv": [4, 13]},
						{"origin": [-17.81996, 10.65809, -3.76016], "size": [1.23962, 1.29752, 2.0446], "inflate": -0.5, "pivot": [-11.73222, 5.69812, 9.21629], "rotation": [0, 0, 67.5], "uv": [4, 13]},
						{"origin": [-9.2423, 12.26777, -3.76016], "size": [1.23962, 1.49264, 2.0446], "inflate": -0.5, "pivot": [-8.7423, 12.76777, -2.1626], "rotation": [0, 0, 90], "uv": [4, 13]},
						{"origin": [-9.2316, 11.41653, -3.76016], "size": [1.5323, 1.49264, 2.0446], "inflate": -0.5, "pivot": [-8.7316, 12.30678, -2.1626], "rotation": [0, 0, -67.5], "uv": [4, 13]},
						{"origin": [-9.40103, 10.95442, -3.76016], "size": [1.43474, 1.78533, 2.0446], "inflate": -0.5, "pivot": [-8.90103, 12.13734, -2.1626], "rotation": [0, 0, -45], "uv": [4, 13]},
						{"origin": [-10.11021, 11.54564, -3.76016], "size": [1.72742, 1.1024, 2.0446], "inflate": -0.5, "pivot": [-9.12241, 12.04564, -2.1626], "rotation": [0, 0, -22.5], "uv": [4, 13]},
						{"origin": [-9.62241, 11.35052, -3.76016], "size": [1.62986, 1.29752, 2.0446], "inflate": -0.5, "pivot": [-9.12241, 12.04564, -2.1626], "rotation": [0, 0, -22.5], "uv": [4, 13]}
					]
				},
				{
					"name": "cover5",
					"parent": "hole5",
					"pivot": [-8.17409, 5.338, 10.22331]
				},
				{
					"name": "hole6",
					"parent": "barrel",
					"pivot": [-9.24245, 12.1377, 0.86585],
					"rotation": [0, -90, 0],
					"cubes": [
						{"origin": [-9.86202, 11.28202, -3.85772], "size": [1.82498, 1.29752, 2.43485], "inflate": -0.5, "uv": [4, 13]},
						{"origin": [-10.15471, 11.28202, -3.85772], "size": [1.5323, 1.19996, 2.43485], "inflate": -0.5, "uv": [4, 13]},
						{"origin": [-12.95329, 10.72983, -3.85772], "size": [1.23962, 1.1024, 2.43485], "inflate": -0.5, "pivot": [-9.39982, 3.23559, 9.31385], "rotation": [0, 0, 22.5], "uv": [4, 13]},
						{"origin": [-9.40103, 11.19033, -3.85772], "size": [3.7762, 1.78533, 2.43485], "inflate": -0.5, "pivot": [-8.90103, 11.79273, -3.35772], "rotation": [0, 0, 45], "uv": [4, 13]}
					]
				},
				{
					"name": "cover6",
					"parent": "hole6",
					"pivot": [-8.17409, 3.97214, 10.32087]
				},
				{
					"name": "hole2",
					"parent": "barrel",
					"pivot": [-5.73025, 18.84502, -21.67073]
				},
				{
					"name": "rightSleeve",
					"parent": "rightArm",
					"pivot": [-5, 22, 0]
				},
				{
					"name": "rightItem",
					"parent": "rightArm",
					"pivot": [-6, 15, 1]
				},
				{
					"name": "jacket",
					"parent": "body",
					"pivot": [0, 24, 0]
				},
				{
					"name": "leftLeg",
					"parent": "root",
					"pivot": [1.9, 12, 0]
				},
				{
					"name": "leftPants",
					"parent": "leftLeg",
					"pivot": [1.9, 12, 0]
				},
				{
					"name": "rightLeg",
					"parent": "root",
					"pivot": [-1.9, 12, 0]
				},
				{
					"name": "rightPants",
					"parent": "rightLeg",
					"pivot": [-1.9, 12, 0]
				}
			]
		}
	]
}